oqclib/__init__.py
oqclib/config.py
oqclib/constants.py
oqclib/encrypt_util.py
oqclib/indicators/macd_dvgc.py
oqclib/indicators/macd_ref.py
oqclib/indicators/model.py
oqclib/market/china.py
oqclib/models/trade.py
oqclib/robot/__init__.py
oqclib/robot/dingtalk.py
oqclib/robot/lark.py
oqclib/robot/slack.py
oqclib/tushare_util.py
oqclib/utils/__init__.py
oqclib/utils/common.py
oqclib/utils/crypto_symbol_util.py
oqclib/utils/datetime_util.py
oqclib/utils/exchanges.py
oqclib/utils/future_symbol_util.py
oqclib/utils/http_util.py
oqclib/utils/math_util.py
oqclib-0.1.125.dist-info/METADATA
oqclib-0.1.125.dist-info/WHEEL
oqclib-0.1.125.dist-info/RECORD
