Metadata-Version: 2.1
Name: oqclib
Version: 0.1.125
Summary: OQC Python Libraries
License: MIT
Author: OQC
Author-email: oqc@hotmail.com
Requires-Python: >=3.9,<3.14
Classifier: License :: OSI Approved :: MIT License
Classifier: Programming Language :: Python :: 3
Classifier: Programming Language :: Python :: 3.9
Classifier: Programming Language :: Python :: 3.10
Classifier: Programming Language :: Python :: 3.11
Classifier: Programming Language :: Python :: 3.12
Classifier: Programming Language :: Python :: 3.13
Requires-Dist: aiohttp (>=3.10.11,<3.11.0)
Requires-Dist: html2text (>=2024.2.26,<2025.0.0)
Requires-Dist: mplfinance (>=0.12.10b0,<0.13.0)
Requires-Dist: pycryptodome (>=3.18.0,<4.0.0)
Requires-Dist: redis (>=5.2.1,<6.0.0)
Requires-Dist: tomli (>=2.0.1,<3.0.0)
Requires-Dist: tzlocal (>=5.3.1,<6.0.0)
